Workbook

Sheet Prévisions Dépenses-Décaiss
C19: Prévisions Dépenses
A25: Elements Periodes | C25: Janvier 1-7 | D25: Janvier 8-15 | E25: Janvier 16-23 | F25: Janvier 24-31 | G25: Fevrier 1-7 | H25: Fevrier 8-15 | I25: Fevrier 16-23 | J25: Fevrier 24-28 | K25: Mars 1-7 | L25: Mars 8-15 | M25: Mars 16-23 | N25: Mars 24-31
A26: Fixes | B26: Salaire Net
B27: IRG
B28: Secu 35%
B29: Abon.tel
B30: Loyer
A31: Total Fixes | C31: =SUM(C26:C30) -> 0 | D31: =SUM(D26:D30) -> 0 | E31: =SUM(E26:E30) -> 0 | F31: =SUM(F26:F30) -> 0 | G31: =SUM(G26:G30) -> 0 | H31: =SUM(H26:H30) -> 0 | I31: =SUM(I26:I30) -> 0 | J31: =SUM(J26:J30) -> 0 | ... N31: =SUM(N26:N30) -> 0
A32: Variables | B32: G50 TAP
B33: G50 TVA
B34: G50 ACOMPTE IBS
B35: Achats materiels
B36: Autres
A37: Total Variables | C37: =SUM(C32:C36) -> 0 | D37: =SUM(D32:D36) -> 0 | E37: =SUM(E32:E36) -> 0 | F37: =SUM(F32:F36) -> 0 | G37: =SUM(G32:G36) -> 0 | H37: =SUM(H32:H36) -> 0 | I37: =SUM(I32:I36) -> 0 | J37: =SUM(J32:J36) -> 0 | ... N37: =SUM(N32:N36) -> 0
A38: Total depenses periode | C38: =C31+C37 -> 0 | D38: =D31+D37 -> 0 | E38: =E31+E37 -> 0 | F38: =F31+F37 -> 0 | G38: =G31+G37 -> 0 | H38: =H31+H37 -> 0 | I38: =I31+I37 -> 0 | J38: =J31+J37 -> 0 | ... N38: =N31+N37 -> 0
A39: Total depenses mois | C39: =C38+D38+E38+F38 -> 0 | G39: =G38+H38+I38+J38 -> 0 | K39: =K38+L38+M38+N38 -> 0
A43: Elements Periodes | C43: Avril 1-7 | D43: Avril 8-15 | E43: Avril 16-23 | F43: Avril 24-30 | G43: Mai 1-7 | H43: Mai 8-15 | I43: Mai 16-23 | J43: Mai 24-31 | K43: Juin 1-7 | L43: Juin 8-15 | M43: Juin 16-23 | N43: Juin 24-30
A44: Fixes | B44: Salaire Net
B45: IRG
B46: Secu 35%
B47: Abon.tel
B48: Loyer
A49: Total Fixes | C49: =SUM(C44:C48) -> 0 | D49: =SUM(D44:D48) -> 0 | E49: =SUM(E44:E48) -> 0 | F49: =SUM(F44:F48) -> 0 | G49: =SUM(G44:G48) -> 0 | H49: =SUM(H44:H48) -> 0 | I49: =SUM(I44:I48) -> 0 | J49: =SUM(J44:J48) -> 0 | ... N49: =SUM(N44:N48) -> 0
A50: Variables | B50: G50 TAP
B51: G50 TVA
B52: G50 ACOMPTE IBS
B53: Achats materiels
B54: Autres
A55: Total Variables | C55: =SUM(C50:C54) -> 0 | D55: =SUM(D50:D54) -> 0 | E55: =SUM(E50:E54) -> 0 | F55: =SUM(F50:F54) -> 0 | G55: =SUM(G50:G54) -> 0 | H55: =SUM(H50:H54) -> 0 | I55: =SUM(I50:I54) -> 0 | J55: =SUM(J50:J54) -> 0 | ... N55: =SUM(N50:N54) -> 0
A56: Total depenses periode | C56: =C49+C55 -> 0 | D56: =D49+D55 -> 0 | E56: =E49+E55 -> 0 | F56: =F49+F55 -> 0 | G56: =G49+G55 -> 0 | H56: =H49+H55 -> 0 | I56: =I49+I55 -> 0 | J56: =J49+J55 -> 0 | ... N56: =N49+N55 -> 0
A57: Total depenses mois | C57: =C56+D56+E56+F56 -> 0 | G57: =G56+H56+I56+J56 -> 0 | K57: =K56+L56+M56+N56 -> 0
A61: Elements Periodes | C61: Juillet 1-7 | D61: Juillet 8-15 | E61: Juillet 16-23 | F61: Juillet 24-31 | G61: Aout 1-7 | H61: Aout 8-15 | I61: Aout 16-23 | J61: Aout 24-31 | K61: Septembre 1-7 | L61: Septembre 8-15 | M61: Septembre 16-23 | N61: Septembre 24-31
A62: Fixes | B62: Salaire Net
B63: IRG
B64: Secu 35%
B65: Abon.tel
B66: Loyer
A67: Total Fixes | C67: =SUM(C62:C66) -> 0 | D67: =SUM(D62:D66) -> 0 | E67: =SUM(E62:E66) -> 0 | F67: =SUM(F62:F66) -> 0 | G67: =SUM(G62:G66) -> 0 | H67: =SUM(H62:H66) -> 0 | I67: =SUM(I62:I66) -> 0 | J67: =SUM(J62:J66) -> 0 | ... N67: =SUM(N62:N66) -> 0
A68: Variables | B68: G50 TAP
B69: G50 TVA
B70: G50 ACOMPTE IBS
B71: Achats materiels
B72: Autres
A73: Total Variables | C73: =SUM(C68:C72) -> 0 | D73: =SUM(D68:D72) -> 0 | E73: =SUM(E68:E72) -> 0 | F73: =SUM(F68:F72) -> 0 | G73: =SUM(G68:G72) -> 0 | H73: =SUM(H68:H72) -> 0 | I73: =SUM(I68:I72) -> 0 | J73: =SUM(J68:J72) -> 0 | ... N73: =SUM(N68:N72) -> 0
A74: Total depenses periode | C74: =C67+C73 -> 0 | D74: =D67+D73 -> 0 | E74: =E67+E73 -> 0 | F74: =F67+F73 -> 0 | G74: =G67+G73 -> 0 | H74: =H67+H73 -> 0 | I74: =I67+I73 -> 0 | J74: =J67+J73 -> 0 | ... N74: =N67+N73 -> 0
A75: Total depenses mois | C75: =C74+D74+E74+F74 -> 0 | G75: =G74+H74+I74+J74 -> 0 | K75: =K74+L74+M74+N74 -> 0
A79: Elements Periodes | C79: Octobre 1-7 | D79: Octobre 8-15 | E79: Octobre 16-23 | F79: Octobre 24-31 | G79: Novembre 1-7 | H79: Novembre 8-15 | I79: Novembre 16-23 | J79: Novembre 24-31 | K79: Decembre 1-7 | L79: Decembre 8-15 | M79: Decembre 16-23 | N79: Decembre 24-31 | O79: janvier 8-15-21 | P79: janvier 16-23-21 | Q79: janvier 24-31-21 | R79: TOTAL
A80: Fixes | B80: Salaire Net | R80: =SUM(C26:N26,C44:N44,C62:N62,Tableau413[[#This Row],[Octobre 1-7]:[janvier 24-31-21]]) -> 0
B81: IRG | R81: =SUM(C27:N27,C45:N45,C63:N63,Tableau413[[#This Row],[Octobre 1-7]:[janvier 24-31-21]]) -> 0
B82: Secu 35% | R82: =SUM(C28:N28,C46:N46,C64:N64,Tableau413[[#This Row],[Octobre 1-7]:[janvier 24-31-21]]) -> 0
B83: Abon.tel | R83: =SUM(C29:N29,C47:N47,C65:N65,Tableau413[[#This Row],[Octobre 1-7]:[janvier 24-31-21]]) -> 0
B84: Loyer | R84: =SUM(C30:N30,C48:N48,C66:N66,Tableau413[[#This Row],[Octobre 1-7]:[janvier 24-31-21]]) -> 0
A85: Total Fixes | R85: =SUM(C31:N31,C49:N49,C67:N67,Tableau413[[#This Row],[Octobre 1-7]:[janvier 24-31-21]]) -> 0
A86: Variables | B86: G50 TAP | R86: =SUM(C32:N32,C50:N50,C68:N68,Tableau413[[#This Row],[Octobre 1-7]:[janvier 24-31-21]]) -> 0
B87: G50 TVA | R87: =SUM(C33:N33,C51:N51,C69:N69,Tableau413[[#This Row],[Octobre 1-7]:[janvier 24-31-21]]) -> 0
B88: G50 ACOMPTE IBS | R88: =SUM(C34:N34,C52:N52,C70:N70,Tableau413[[#This Row],[Octobre 1-7]:[janvier 24-31-21]]) -> 0
B89: Achats materiels | R89: =SUM(C35:N35,C53:N53,C71:N71,Tableau413[[#This Row],[Octobre 1-7]:[janvier 24-31-21]]) -> 0
B90: Autres | R90: =SUM(C36:N36,F54:N54,C72:N72,Tableau413[[#This Row],[Octobre 1-7]:[janvier 24-31-21]]) -> 0
A91: Total Variables | C91: =SUM(C86:C90) -> 0 | D91: =SUM(D86:D90) -> 0 | E91: =SUM(E86:E90) -> 0 | F91: =SUM(F86:F90) -> 0 | G91: =SUM(G86:G90) -> 0 | H91: =SUM(H86:H90) -> 0 | I91: =SUM(I86:I90) -> 0 | J91: =SUM(J86:J90) -> 0 | ... Q91: =SUM(Q86:Q90) -> 0 | R91: =SUM(C37:N37,C55:N55,C73:N73,Tableau413[[#This Row],[Octobre 1-7]:[janvier 24-31-21]]) -> 0
A92: Total depenses periode | C92: =C85+C91 -> 0 | D92: =D85+D91 -> 0 | E92: =E85+E91 -> 0 | F92: =F85+F91 -> 0 | G92: =G85+G91 -> 0 | H92: =H85+H91 -> 0 | I92: =I85+I91 -> 0 | J92: =J85+J91 -> 0 | ... Q92: =Q85+Q91 -> 0 | R92: =SUM(C38:N38,C56:N56,C74:N74,Tableau413[[#This Row],[Octobre 1-7]:[janvier 24-31-21]]) -> 0
A93: Total depenses mois | C93: =C92+D92+E92+F92 -> 0 | G93: =G92+H92+I92+J92 -> 0 | K93: =K92+L92+M92+N92 -> 0 | R93: =R85+R91 -> 0

Sheet Prévisions Entrées-Encaiss
C17: Prévisions Encaissements
A24: Elements Periodes | C24: Janvier 1-7 | D24: Janvier 8-15 | E24: Janvier 16-23 | F24: Janvier 24-31 | G24: Fevrier 1-7 | H24: Fevrier 8-15 | I24: Fevrier 16-23 | J24: Fevrier 24-28 | K24: Mars 1-7 | L24: Mars 8-15 | M24: Mars 16-23 | N24: Mars 24-31
A25: Clients | B25: Henkel
B26: KNAUF
B27: MyTeamConnect
B28: Lafarge
B29: DIGITAL NATIVES
B30: Beyond
B31: Kimmco
B32: Insersite
B33: In Solutions
B34: Impact design
A35: Autres ( tva déductibles)
A36: Total encaissements periode HT | C36: =SUM(Tableau13[Janvier 1-7]) -> 0 | D36: =SUM(Tableau13[Janvier 8-15]) -> 0 | E36: =SUM(Tableau13[Janvier 16-23]) -> 0 | F36: =SUM(Tableau13[Janvier 24-31]) -> 0 | G36: =SUM(Tableau13[Fevrier 1-7]) -> 0 | H36: =SUM(Tableau13[Fevrier 8-15]) -> 0 | I36: =SUM(Tableau13[Fevrier 16-23]) -> 0 | J36: =SUM(Tableau13[Fevrier 24-28]) -> 0 | K36: =SUM(Tableau13[Mars 1-7]) -> 0 | L36: =SUM(Tableau13[Mars 8-15]) -> 0 | M36: =SUM(Tableau13[Mars 16-23]) -> 0 | N36: =SUM(Tableau13[Mars 24-31]) -> 0
A37: Total encaissements mois | C37: =SUM(C36:F36) -> 0 | G37: =SUM(G36:J36) -> 0 | K37: =SUM(K36:N36) -> 0
A41: Elements Periodes | C41: Avril 1-7 | D41: Avril 8-15 | E41: Avril 16-23 | F41: Avril 24-30 | G41: Mai 1-7 | H41: Mai 8-15 | I41: Mai 16-23 | J41: Mai 24-31 | K41: Juin 1-7 | L41: Juin 8-15 | M41: Juin 16-23 | N41: Juin 24-30
A42: Clients | B42: Henkel
B43: KNAUF
B44: MyTeamConnect
B45: Lafarge
B46: DIGITAL NATIVES
B47: Beyond
B48: Kimmco
B49: Insersite
B50: In Solutions
B51: Impact design
A52: Autres ( tva déductibles)
A53: Total encaissements periode | C53: =SUM(C42:C52) -> 0 | D53: =SUM(D42:D52) -> 0 | E53: =SUM(E42:E52) -> 0 | F53: =SUM(F42:F52) -> 0 | G53: =SUM(G42:G52) -> 0 | H53: =SUM(H42:H52) -> 0 | I53: =SUM(I42:I52) -> 0 | J53: =SUM(J42:J52) -> 0 | ... N53: =SUM(N42:N52) -> 0
A54: Total encaissements mois | C54: =SUM(C53:F53) -> 0 | G54: =SUM(G53:J53) -> 0 | K54: =SUM(K53:N53) -> 0
A58: Elements Periodes | C58: Juillet 1-7 | D58: Juillet 8-15 | E58: Juillet 16-23 | F58: Juillet 24-31 | G58: Aout 1-7 | H58: Aout 8-15 | I58: Aout 16-23 | J58: Aout 24-31 | K58: Septembre 1-7 | L58: Septembre 8-15 | M58: Septembre 16-23 | N58: Septembre 24-30
A59: Clients | B59: Henkel
B60: KNAUF
B61: MyTeamConnect
B62: Lafarge
B63: DIGITAL NATIVES
B64: Beyond
B65: Kimmco
B66: Insersite
B67: In Solutions
B68: Impact design
A69: Autres ( tva déductibles)
A70: Total encaissements periode | C70: =SUM(C59:C69) -> 0 | D70: =SUM(D59:D69) -> 0 | E70: =SUM(E59:E69) -> 0 | F70: =SUM(F59:F69) -> 0 | G70: =SUM(G59:G69) -> 0 | H70: =SUM(H59:H69) -> 0 | I70: =SUM(I59:I69) -> 0 | J70: =SUM(J59:J69) -> 0 | ... N70: =SUM(N59:N69) -> 0
A71: Total encaissements mois | C71: =SUM(C70:F70) -> 0 | G71: =SUM(G70:J70) -> 0 | K71: =SUM(K70:N70) -> 0
A75: Elements Periodes | C75: Octobre 1-7 | D75: Octobre 8-15 | E75: Octobre 16-23 | F75: Octobre 24-30 | G75: Novembre 1-7 | H75: Novembre 8-15 | I75: Novembre 16-23 | J75: Novembre 24-30 | K75: Decembre 1-7 | L75: Decembre 8-15 | M75: Decembre 16-23 | N75: Decembre 24-30 | O75: Janvier 1-7-21 | P75: Janvier 8-15-21 | Q75: Janvier 16-23-21 | R75: Janvier 24-30-21 | S75: TOTAL
A76: Clients | B76: Henkel | S76: =SUM(C25:N25,C42:N42,C59:N59,C76:R76) -> 0
B77: KNAUF | S77: =SUM(C26:N26,C43:N43,C60:N60,C77:R77) -> 0
B78: MyTeamConnect | S78: =SUM(C27:N27,C44:N44,C61:N61,C78:R78) -> 0
B79: Lafarge | S79: =SUM(C28:N28,C45:N45,C62:N62,C79:R79) -> 0
B80: DIGITAL NATIVES | S80: =SUM(C29:N29,C46:N46,C63:N63,C80:R80) -> 0
B81: Beyond | S81: =SUM(C30:N30,C47:N47,C64:N64,C81:R81) -> 0
B82: Kimmco | S82: =SUM(C31:N31,C48:N48,C65:N65,C82:R82) -> 0
B83: Insersite | S83: =SUM(C32:N32,C49:N49,C66:N66,C83:R83) -> 0
B84: In Solutions | S84: =SUM(C33:N33,C50:N50,C67:N67,C84:R84) -> 0
B85: Impact design | S85: =SUM(C34:N34,C51:N51,C68:N68,C85:R85) -> 0
A86: Autres ( tva déductibles) | S86: =SUM(C35:N35,C52:N52,C69:N69,C86:R86) -> 0
A87: Total encaissements periode | C87: =SUM(C76:C86) -> 0 | D87: =SUM(D76:D86) -> 0 | E87: =SUM(E76:E86) -> 0 | F87: =SUM(F76:F86) -> 0 | G87: =SUM(G76:G86) -> 0 | H87: =SUM(H76:H86) -> 0 | I87: =SUM(I76:I86) -> 0 | J87: =SUM(J76:J86) -> 0 | ... S87: =SUM(S76:S86) -> 0
A88: Total encaissements mois | C88: =SUM(C87:F87) -> 0 | G88: =SUM(G87:J87) -> 0 | K88: =SUM(K87:N87) -> 0 | O88: =SUM(O87:R87) -> 0 | S88: =SUM(S76:S86) -> 0

Sheet Flux de trésorerie
D14: FLUX DE TRESORERIE ET GESTION BUDGETAIRE
A22: Elements Periodes | C22: Janvier 1-7 | D22: Janvier 8-15 | E22: Janvier 16-23 | F22: Janvier 24-31 | G22: Fevrier 1-7 | H22: Fevrier 8-15 | I22: Fevrier 16-23 | J22: Fevrier 24-28 | K22: Mars 1-7 | L22: Mars 8-15 | M22: Mars 16-23 | N22: Mars 24-31
A23: Encaissements
A24: Clients | B24: Henkel | C24: ='Prévisions Entrées-Encaiss'!C25 -> 0 | D24: ='Prévisions Entrées-Encaiss'!D25 -> 0 | E24: ='Prévisions Entrées-Encaiss'!E25 -> 0 | F24: ='Prévisions Entrées-Encaiss'!F25 -> 0 | G24: ='Prévisions Entrées-Encaiss'!G25 -> 0 | H24: ='Prévisions Entrées-Encaiss'!H25 -> 0 | I24: ='Prévisions Entrées-Encaiss'!I25 -> 0 | J24: ='Prévisions Entrées-Encaiss'!J25 -> 0 | ... N24: ='Prévisions Entrées-Encaiss'!N25 -> 0
B25: KNAUF | C25: ='[1]Prévisions Entrées-Encaiss'!C26 -> 0 | D25: ='[1]Prévisions Entrées-Encaiss'!D26 -> 0 | E25: ='[1]Prévisions Entrées-Encaiss'!E26 -> 0 | F25: ='[1]Prévisions Entrées-Encaiss'!F26 -> 0 | G25: ='[1]Prévisions Entrées-Encaiss'!G26 -> 0 | H25: ='[1]Prévisions Entrées-Encaiss'!H26 -> 0 | I25: ='[1]Prévisions Entrées-Encaiss'!I26 -> 0 | J25: ='[1]Prévisions Entrées-Encaiss'!J26 -> 0 | ... N25: ='[1]Prévisions Entrées-Encaiss'!N26 -> 0
B26: MyTeamConnect | C26: ='[1]Prévisions Entrées-Encaiss'!C27 -> 0 | D26: ='[1]Prévisions Entrées-Encaiss'!D27 -> 0 | E26: ='[1]Prévisions Entrées-Encaiss'!E27 -> 0 | F26: ='[1]Prévisions Entrées-Encaiss'!F27 -> 0 | G26: ='[1]Prévisions Entrées-Encaiss'!G27 -> 0 | H26: ='[1]Prévisions Entrées-Encaiss'!H27 -> 0 | I26: ='[1]Prévisions Entrées-Encaiss'!I27 -> 0 | J26: ='[1]Prévisions Entrées-Encaiss'!J27 -> 0 | ... N26: ='[1]Prévisions Entrées-Encaiss'!N27 -> 0
B27: Lafarge | C27: ='[1]Prévisions Entrées-Encaiss'!C28 -> 0 | D27: ='[1]Prévisions Entrées-Encaiss'!D28 -> 0 | E27: ='[1]Prévisions Entrées-Encaiss'!E28 -> 0 | F27: ='[1]Prévisions Entrées-Encaiss'!F28 -> 0 | G27: ='[1]Prévisions Entrées-Encaiss'!G28 -> 0 | H27: ='[1]Prévisions Entrées-Encaiss'!H28 -> 0 | I27: ='[1]Prévisions Entrées-Encaiss'!I28 -> 0 | J27: ='[1]Prévisions Entrées-Encaiss'!J28 -> 0 | ... N27: ='[1]Prévisions Entrées-Encaiss'!N28 -> 0
B28: DIGITAL NATIVES | C28: ='[1]Prévisions Entrées-Encaiss'!C29 -> 0 | D28: ='[1]Prévisions Entrées-Encaiss'!D29 -> 0 | E28: ='[1]Prévisions Entrées-Encaiss'!E29 -> 0 | F28: ='[1]Prévisions Entrées-Encaiss'!F29 -> 0 | G28: ='[1]Prévisions Entrées-Encaiss'!G29 -> 0 | H28: ='[1]Prévisions Entrées-Encaiss'!H29 -> 0 | I28: ='[1]Prévisions Entrées-Encaiss'!I29 -> 0 | J28: ='[1]Prévisions Entrées-Encaiss'!J29 -> 0 | ... N28: ='[1]Prévisions Entrées-Encaiss'!N29 -> 0
B29: Beyond | C29: ='[1]Prévisions Entrées-Encaiss'!C30 -> 0 | D29: ='[1]Prévisions Entrées-Encaiss'!D30 -> 0 | E29: ='[1]Prévisions Entrées-Encaiss'!E30 -> 0 | F29: ='[1]Prévisions Entrées-Encaiss'!F30 -> 0 | G29: ='[1]Prévisions Entrées-Encaiss'!G30 -> 0 | H29: ='[1]Prévisions Entrées-Encaiss'!H30 -> 0 | I29: ='[1]Prévisions Entrées-Encaiss'!I30 -> 0 | J29: ='[1]Prévisions Entrées-Encaiss'!J30 -> 0 | ... N29: ='[1]Prévisions Entrées-Encaiss'!N30 -> 0
B30: Kimmco | C30: ='[1]Prévisions Entrées-Encaiss'!C31 -> 0 | D30: ='[1]Prévisions Entrées-Encaiss'!D31 -> 0 | E30: ='[1]Prévisions Entrées-Encaiss'!E31 -> 0 | F30: ='[1]Prévisions Entrées-Encaiss'!F31 -> 0 | G30: ='[1]Prévisions Entrées-Encaiss'!G31 -> 0 | H30: ='[1]Prévisions Entrées-Encaiss'!H31 -> 0 | I30: ='[1]Prévisions Entrées-Encaiss'!I31 -> 0 | J30: ='[1]Prévisions Entrées-Encaiss'!J31 -> 0 | ... N30: ='[1]Prévisions Entrées-Encaiss'!N31 -> 0
B31: Insersite | C31: ='[1]Prévisions Entrées-Encaiss'!C32 -> 0 | D31: ='[1]Prévisions Entrées-Encaiss'!D32 -> 0 | E31: ='[1]Prévisions Entrées-Encaiss'!E32 -> 0 | F31: ='[1]Prévisions Entrées-Encaiss'!F32 -> 0 | G31: ='[1]Prévisions Entrées-Encaiss'!G32 -> 0 | H31: ='[1]Prévisions Entrées-Encaiss'!H32 -> 0 | I31: ='[1]Prévisions Entrées-Encaiss'!I32 -> 0 | J31: ='[1]Prévisions Entrées-Encaiss'!J32 -> 0 | ... N31: ='[1]Prévisions Entrées-Encaiss'!N32 -> 0
B32: In Solutions | C32: ='[1]Prévisions Entrées-Encaiss'!C33 -> 0 | D32: ='[1]Prévisions Entrées-Encaiss'!D33 -> 0 | E32: ='[1]Prévisions Entrées-Encaiss'!E33 -> 0 | F32: ='[1]Prévisions Entrées-Encaiss'!F33 -> 0 | G32: ='[1]Prévisions Entrées-Encaiss'!G33 -> 0 | H32: ='[1]Prévisions Entrées-Encaiss'!H33 -> 0 | I32: ='[1]Prévisions Entrées-Encaiss'!I33 -> 0 | J32: ='[1]Prévisions Entrées-Encaiss'!J33 -> 0 | ... N32: ='[1]Prévisions Entrées-Encaiss'!N33 -> 0
B33: Impact design | C33: ='[1]Prévisions Entrées-Encaiss'!C34 -> 0 | D33: ='[1]Prévisions Entrées-Encaiss'!D34 -> 0 | E33: ='[1]Prévisions Entrées-Encaiss'!E34 -> 0 | F33: ='[1]Prévisions Entrées-Encaiss'!F34 -> 0 | G33: ='[1]Prévisions Entrées-Encaiss'!G34 -> 0 | H33: ='[1]Prévisions Entrées-Encaiss'!H34 -> 0 | I33: ='[1]Prévisions Entrées-Encaiss'!I34 -> 0 | J33: ='[1]Prévisions Entrées-Encaiss'!J34 -> 0 | ... N33: ='[1]Prévisions Entrées-Encaiss'!N34 -> 0
A34: Autres ( tva déductibles,,,) | C34: ='[1]Prévisions Entrées-Encaiss'!C35 -> 0 | D34: ='[1]Prévisions Entrées-Encaiss'!D35 -> 0 | E34: ='[1]Prévisions Entrées-Encaiss'!E35 -> 0 | F34: ='[1]Prévisions Entrées-Encaiss'!F35 -> 0 | G34: ='[1]Prévisions Entrées-Encaiss'!G35 -> 0 | H34: ='[1]Prévisions Entrées-Encaiss'!H35 -> 0 | I34: ='[1]Prévisions Entrées-Encaiss'!I35 -> 0 | J34: ='[1]Prévisions Entrées-Encaiss'!J35 -> 0 | ... N34: ='[1]Prévisions Entrées-Encaiss'!N35 -> 0
A35: TOTAL Encaissements | C35: =SUM(C24:C34) -> 0 | D35: =SUM(D24:D34) -> 0 | E35: =SUM(E24:E34) -> 0 | F35: =SUM(F24:F34) -> 0 | G35: =SUM(G24:G34) -> 0 | H35: =SUM(H24:H34) -> 0 | I35: =SUM(I24:I34) -> 0 | J35: =SUM(J24:J34) -> 0 | ... N35: =SUM(N24:N34) -> 0
A36: Décaissements
A37: Salaire Net | C37: ='Prévisions Dépenses-Décaiss'!C26 -> 0 | D37: ='Prévisions Dépenses-Décaiss'!D26 -> 0 | E37: ='Prévisions Dépenses-Décaiss'!E26 -> 0 | F37: ='Prévisions Dépenses-Décaiss'!F26 -> 0 | G37: ='Prévisions Dépenses-Décaiss'!G26 -> 0 | H37: ='Prévisions Dépenses-Décaiss'!H26 -> 0 | I37: ='Prévisions Dépenses-Décaiss'!I26 -> 0 | J37: ='Prévisions Dépenses-Décaiss'!J26 -> 0 | ... N37: ='Prévisions Dépenses-Décaiss'!N26 -> 0
A38: IRG G50 | C38: ='[1]Prévisions Dépenses-Décaiss'!C27 -> 0 | D38: ='[1]Prévisions Dépenses-Décaiss'!D27 -> 0 | E38: ='[1]Prévisions Dépenses-Décaiss'!E27 -> 0 | F38: ='[1]Prévisions Dépenses-Décaiss'!F27 -> 0 | G38: ='[1]Prévisions Dépenses-Décaiss'!G27 -> 0 | H38: ='[1]Prévisions Dépenses-Décaiss'!H27 -> 0 | I38: ='[1]Prévisions Dépenses-Décaiss'!I27 -> 0 | J38: ='[1]Prévisions Dépenses-Décaiss'!J27 -> 0 | ... N38: ='[1]Prévisions Dépenses-Décaiss'!N27 -> 0
A39: Secu 35% | C39: ='[1]Prévisions Dépenses-Décaiss'!C28 -> 0 | D39: ='[1]Prévisions Dépenses-Décaiss'!D28 -> 0 | E39: ='[1]Prévisions Dépenses-Décaiss'!E28 -> 0 | F39: ='[1]Prévisions Dépenses-Décaiss'!F28 -> 0 | G39: ='[1]Prévisions Dépenses-Décaiss'!G28 -> 0 | H39: ='[1]Prévisions Dépenses-Décaiss'!H28 -> 0 | I39: ='[1]Prévisions Dépenses-Décaiss'!I28 -> 0 | J39: ='[1]Prévisions Dépenses-Décaiss'!J28 -> 0 | ... N39: ='[1]Prévisions Dépenses-Décaiss'!N28 -> 0
A40: Abon.tel | C40: ='[1]Prévisions Dépenses-Décaiss'!C29 -> 0 | D40: ='[1]Prévisions Dépenses-Décaiss'!D29 -> 0 | E40: ='[1]Prévisions Dépenses-Décaiss'!E29 -> 0 | F40: ='[1]Prévisions Dépenses-Décaiss'!F29 -> 0 | G40: ='[1]Prévisions Dépenses-Décaiss'!G29 -> 0 | H40: ='[1]Prévisions Dépenses-Décaiss'!H29 -> 0 | I40: ='[1]Prévisions Dépenses-Décaiss'!I29 -> 0 | J40: ='[1]Prévisions Dépenses-Décaiss'!J29 -> 0 | ... N40: ='[1]Prévisions Dépenses-Décaiss'!N29 -> 0
A41: Loyer | C41: ='[1]Prévisions Dépenses-Décaiss'!C30 -> 0 | D41: ='[1]Prévisions Dépenses-Décaiss'!D30 -> 0 | E41: ='[1]Prévisions Dépenses-Décaiss'!E30 -> 0 | F41: ='[1]Prévisions Dépenses-Décaiss'!F30 -> 0 | G41: ='[1]Prévisions Dépenses-Décaiss'!G30 -> 0 | H41: ='[1]Prévisions Dépenses-Décaiss'!H30 -> 0 | I41: ='[1]Prévisions Dépenses-Décaiss'!I30 -> 0 | J41: ='[1]Prévisions Dépenses-Décaiss'!J30 -> 0 | ... N41: ='[1]Prévisions Dépenses-Décaiss'!N30 -> 0
A42: G50 Hors IRG | B42: TAP | C42: ='[1]Prévisions Dépenses-Décaiss'!C32 -> 0 | D42: ='[1]Prévisions Dépenses-Décaiss'!D32 -> 0 | E42: ='[1]Prévisions Dépenses-Décaiss'!E32 -> 0 | F42: ='[1]Prévisions Dépenses-Décaiss'!F32 -> 0 | G42: ='[1]Prévisions Dépenses-Décaiss'!G32 -> 0 | H42: ='[1]Prévisions Dépenses-Décaiss'!H32 -> 0 | I42: ='[1]Prévisions Dépenses-Décaiss'!I32 -> 0 | J42: ='[1]Prévisions Dépenses-Décaiss'!J32 -> 0 | ... N42: ='[1]Prévisions Dépenses-Décaiss'!N32 -> 0
B43: TVA | C43: ='[1]Prévisions Dépenses-Décaiss'!C33 -> 0 | D43: ='[1]Prévisions Dépenses-Décaiss'!D33 -> 0 | E43: ='[1]Prévisions Dépenses-Décaiss'!E33 -> 0 | F43: ='[1]Prévisions Dépenses-Décaiss'!F33 -> 0 | G43: ='[1]Prévisions Dépenses-Décaiss'!G33 -> 0 | H43: ='[1]Prévisions Dépenses-Décaiss'!H33 -> 0 | I43: ='[1]Prévisions Dépenses-Décaiss'!I33 -> 0 | J43: ='[1]Prévisions Dépenses-Décaiss'!J33 -> 0 | ... N43: ='[1]Prévisions Dépenses-Décaiss'!N33 -> 0
B44: Acompte IBS | C44: ='[1]Prévisions Dépenses-Décaiss'!C34 -> 0 | D44: ='[1]Prévisions Dépenses-Décaiss'!D34 -> 0 | E44: ='[1]Prévisions Dépenses-Décaiss'!E34 -> 0 | F44: ='[1]Prévisions Dépenses-Décaiss'!F34 -> 0 | G44: ='[1]Prévisions Dépenses-Décaiss'!G34 -> 0 | H44: ='[1]Prévisions Dépenses-Décaiss'!H34 -> 0 | I44: ='[1]Prévisions Dépenses-Décaiss'!I34 -> 0 | J44: ='[1]Prévisions Dépenses-Décaiss'!J34 -> 0 | ... N44: ='[1]Prévisions Dépenses-Décaiss'!N34 -> 0
A45: Achats materiels | C45: ='[1]Prévisions Dépenses-Décaiss'!C35 -> 0 | D45: ='[1]Prévisions Dépenses-Décaiss'!D35 -> 0 | E45: ='[1]Prévisions Dépenses-Décaiss'!E35 -> 0 | F45: ='[1]Prévisions Dépenses-Décaiss'!F35 -> 0 | G45: ='[1]Prévisions Dépenses-Décaiss'!G35 -> 0 | H45: ='[1]Prévisions Dépenses-Décaiss'!H35 -> 0 | I45: ='[1]Prévisions Dépenses-Décaiss'!I35 -> 0 | J45: ='[1]Prévisions Dépenses-Décaiss'!J35 -> 0 | ... N45: ='[1]Prévisions Dépenses-Décaiss'!N35 -> 0
A46: Autres | C46: ='[1]Prévisions Dépenses-Décaiss'!C36 -> 0 | D46: ='[1]Prévisions Dépenses-Décaiss'!D36 -> 0 | E46: ='[1]Prévisions Dépenses-Décaiss'!E36 -> 0 | F46: ='[1]Prévisions Dépenses-Décaiss'!F36 -> 0 | G46: ='[1]Prévisions Dépenses-Décaiss'!G36 -> 0 | H46: ='[1]Prévisions Dépenses-Décaiss'!H36 -> 0 | I46: ='[1]Prévisions Dépenses-Décaiss'!I36 -> 0 | J46: ='[1]Prévisions Dépenses-Décaiss'!J36 -> 0 | ... N46: ='[1]Prévisions Dépenses-Décaiss'!N36 -> 0
A47: TOTAL Décaissements | C47: =SUM(C37:C46) -> 0 | D47: =SUM(D37:D46) -> 0 | E47: =SUM(E37:E46) -> 0 | F47: =SUM(F37:F46) -> 0 | G47: =SUM(G37:G46) -> 0 | H47: =SUM(H37:H46) -> 0 | I47: =SUM(I37:I46) -> 0 | J47: =SUM(J37:J46) -> 0 | ... N47: =SUM(N37:N46) -> 0
A48: Trésorerie initiale | D48: =C52 -> 0 | E48: =D52 -> 0 | F48: =E52 -> 0 | G48: =F52 -> 0 | H48: =G52 -> 0 | I48: =H52 -> 0 | J48: =I52 -> 0 | K48: =J52 -> 0 | ... N48: =M52 -> 0
A49: Encaissements | C49: =C35 -> 0 | D49: =D35 -> 0 | E49: =E35 -> 0 | F49: =F35 -> 0 | G49: =G35 -> 0 | H49: =H35 -> 0 | I49: =I35 -> 0 | J49: =J35 -> 0 | ... N49: =N35 -> 0
A50: Décaissements | C50: =C47 -> 0 | D50: =D47 -> 0 | E50: =E47 -> 0 | F50: =F47 -> 0 | G50: =G47 -> 0 | H50: =H47 -> 0 | I50: =I47 -> 0 | J50: =J47 -> 0 | ... N50: =N47 -> 0
A51: Solde periode | C51: =C49-C50 -> 0 | D51: =D49-D50 -> 0 | E51: =E49-E50 -> 0 | F51: =F49-F50 -> 0 | G51: =G49-G50 -> 0 | H51: =H49-H50 -> 0 | I51: =I49-I50 -> 0 | J51: =J49-J50 -> 0 | ... N51: =N49-N50 -> 0
A52: Trésorerie finale | C52: =C48+C51 -> 0 | D52: =D48+D51 -> 0 | E52: =E48+E51 -> 0 | F52: =F48+F51 -> 0 | G52: =G48+G51 -> 0 | H52: =H48+H51 -> 0 | I52: =I48+I51 -> 0 | J52: =J48+J51 -> 0 | ... N52: =N48+N51 -> 0
A57: Elements Periodes | C57: Avril 1-7 | D57: Avril 8-15 | E57: Avril 16-23 | F57: Avril 24-30 | G57: Mai 1-7 | H57: Mai 8-15 | I57: Mai 16-23 | J57: Mai 24-31 | K57: Juin 1-7 | L57: Juin 8-15 | M57: Juin 16-23 | N57: Juin 24-30
A58: Encaissements
A59: Clients | B59: Henkel | C59: ='[1]Prévisions Entrées-Encaiss'!C42 -> 0 | D59: ='[1]Prévisions Entrées-Encaiss'!D42 -> 0 | E59: ='[1]Prévisions Entrées-Encaiss'!E42 -> 0 | F59: ='[1]Prévisions Entrées-Encaiss'!F42 -> 0 | G59: ='[1]Prévisions Entrées-Encaiss'!G42 -> 0 | H59: ='[1]Prévisions Entrées-Encaiss'!H42 -> 0 | I59: ='[1]Prévisions Entrées-Encaiss'!I42 -> 0 | J59: ='[1]Prévisions Entrées-Encaiss'!J42 -> 0 | ... N59: ='[1]Prévisions Entrées-Encaiss'!N42 -> 0
B60: KNAUF | C60: ='[1]Prévisions Entrées-Encaiss'!C43 -> 0 | D60: ='[1]Prévisions Entrées-Encaiss'!D43 -> 0 | E60: ='[1]Prévisions Entrées-Encaiss'!E43 -> 0 | F60: ='[1]Prévisions Entrées-Encaiss'!F43 -> 0 | G60: ='[1]Prévisions Entrées-Encaiss'!G43 -> 0 | H60: ='[1]Prévisions Entrées-Encaiss'!H43 -> 0 | I60: ='[1]Prévisions Entrées-Encaiss'!I43 -> 0 | J60: ='[1]Prévisions Entrées-Encaiss'!J43 -> 0 | ... N60: ='[1]Prévisions Entrées-Encaiss'!N43 -> 0
B61: MyTeamConnect | C61: ='[1]Prévisions Entrées-Encaiss'!C44 -> 0 | D61: ='[1]Prévisions Entrées-Encaiss'!D44 -> 0 | E61: ='[1]Prévisions Entrées-Encaiss'!E44 -> 0 | F61: ='[1]Prévisions Entrées-Encaiss'!F44 -> 0 | G61: ='[1]Prévisions Entrées-Encaiss'!G44 -> 0 | H61: ='[1]Prévisions Entrées-Encaiss'!H44 -> 0 | I61: ='[1]Prévisions Entrées-Encaiss'!I44 -> 0 | J61: ='[1]Prévisions Entrées-Encaiss'!J44 -> 0 | ... N61: ='[1]Prévisions Entrées-Encaiss'!N44 -> 0
B62: Lafarge | C62: ='[1]Prévisions Entrées-Encaiss'!C45 -> 0 | D62: ='[1]Prévisions Entrées-Encaiss'!D45 -> 0 | E62: ='[1]Prévisions Entrées-Encaiss'!E45 -> 0 | F62: ='[1]Prévisions Entrées-Encaiss'!F45 -> 0 | G62: ='[1]Prévisions Entrées-Encaiss'!G45 -> 0 | H62: ='[1]Prévisions Entrées-Encaiss'!H45 -> 0 | I62: ='[1]Prévisions Entrées-Encaiss'!I45 -> 0 | J62: ='[1]Prévisions Entrées-Encaiss'!J45 -> 0 | ... N62: ='[1]Prévisions Entrées-Encaiss'!N45 -> 0
B63: DIGITAL NATIVES | C63: ='[1]Prévisions Entrées-Encaiss'!C46 -> 0 | D63: ='[1]Prévisions Entrées-Encaiss'!D46 -> 0 | E63: ='[1]Prévisions Entrées-Encaiss'!E46 -> 0 | F63: ='[1]Prévisions Entrées-Encaiss'!F46 -> 0 | G63: ='[1]Prévisions Entrées-Encaiss'!G46 -> 0 | H63: ='[1]Prévisions Entrées-Encaiss'!H46 -> 0 | I63: ='[1]Prévisions Entrées-Encaiss'!I46 -> 0 | J63: ='[1]Prévisions Entrées-Encaiss'!J46 -> 0 | ... N63: ='[1]Prévisions Entrées-Encaiss'!N46 -> 0
B64: Beyond | C64: ='[1]Prévisions Entrées-Encaiss'!C47 -> 0 | D64: ='[1]Prévisions Entrées-Encaiss'!D47 -> 0 | E64: ='[1]Prévisions Entrées-Encaiss'!E47 -> 0 | F64: ='[1]Prévisions Entrées-Encaiss'!F47 -> 0 | G64: ='[1]Prévisions Entrées-Encaiss'!G47 -> 0 | H64: ='[1]Prévisions Entrées-Encaiss'!H47 -> 0 | I64: ='[1]Prévisions Entrées-Encaiss'!I47 -> 0 | J64: ='[1]Prévisions Entrées-Encaiss'!J47 -> 0 | ... N64: ='[1]Prévisions Entrées-Encaiss'!N47 -> 0
B65: Kimmco | C65: ='[1]Prévisions Entrées-Encaiss'!C48 -> 0 | D65: ='[1]Prévisions Entrées-Encaiss'!D48 -> 0 | E65: ='[1]Prévisions Entrées-Encaiss'!E48 -> 0 | F65: ='[1]Prévisions Entrées-Encaiss'!F48 -> 0 | G65: ='[1]Prévisions Entrées-Encaiss'!G48 -> 0 | H65: ='[1]Prévisions Entrées-Encaiss'!H48 -> 0 | I65: ='[1]Prévisions Entrées-Encaiss'!I48 -> 0 | J65: ='[1]Prévisions Entrées-Encaiss'!J48 -> 0 | ... N65: ='[1]Prévisions Entrées-Encaiss'!N48 -> 0
B66: Insersite/Frere | C66: ='[1]Prévisions Entrées-Encaiss'!C49 -> 0 | D66: ='[1]Prévisions Entrées-Encaiss'!D49 -> 0 | E66: ='[1]Prévisions Entrées-Encaiss'!E49 -> 0 | F66: ='[1]Prévisions Entrées-Encaiss'!F49 -> 0 | G66: ='[1]Prévisions Entrées-Encaiss'!G49 -> 0 | H66: ='[1]Prévisions Entrées-Encaiss'!H49 -> 0 | I66: ='[1]Prévisions Entrées-Encaiss'!I49 -> 0 | J66: ='[1]Prévisions Entrées-Encaiss'!J49 -> 0 | ... N66: ='[1]Prévisions Entrées-Encaiss'!N49 -> 0
B67: In Solutions | C67: ='[1]Prévisions Entrées-Encaiss'!C50 -> 0 | D67: ='[1]Prévisions Entrées-Encaiss'!D50 -> 0 | E67: ='[1]Prévisions Entrées-Encaiss'!E50 -> 0 | F67: ='[1]Prévisions Entrées-Encaiss'!F50 -> 0 | G67: ='[1]Prévisions Entrées-Encaiss'!G50 -> 0 | H67: ='[1]Prévisions Entrées-Encaiss'!H50 -> 0 | I67: ='[1]Prévisions Entrées-Encaiss'!I50 -> 0 | J67: ='[1]Prévisions Entrées-Encaiss'!J50 -> 0 | ... N67: ='[1]Prévisions Entrées-Encaiss'!N50 -> 0
B68: Impact design | C68: ='[1]Prévisions Entrées-Encaiss'!C51 -> 0 | D68: ='[1]Prévisions Entrées-Encaiss'!D51 -> 0 | E68: ='[1]Prévisions Entrées-Encaiss'!E51 -> 0 | F68: ='[1]Prévisions Entrées-Encaiss'!F51 -> 0 | G68: ='[1]Prévisions Entrées-Encaiss'!G51 -> 0 | H68: ='[1]Prévisions Entrées-Encaiss'!H51 -> 0 | I68: ='[1]Prévisions Entrées-Encaiss'!I51 -> 0 | J68: ='[1]Prévisions Entrées-Encaiss'!J51 -> 0 | ... N68: ='[1]Prévisions Entrées-Encaiss'!N51 -> 0
A69: Autres ( tva déductibles,,,) | C69: ='[1]Prévisions Entrées-Encaiss'!C52 -> 0 | D69: ='[1]Prévisions Entrées-Encaiss'!D52 -> 0 | E69: ='[1]Prévisions Entrées-Encaiss'!E52 -> 0 | F69: ='[1]Prévisions Entrées-Encaiss'!F52 -> 0 | G69: ='[1]Prévisions Entrées-Encaiss'!G52 -> 0 | H69: ='[1]Prévisions Entrées-Encaiss'!H52 -> 0 | I69: ='[1]Prévisions Entrées-Encaiss'!I52 -> 0 | J69: ='[1]Prévisions Entrées-Encaiss'!J52 -> 0 | ... N69: ='[1]Prévisions Entrées-Encaiss'!N52 -> 0
A70: TOTAL Encaissements | C70: =SUM(C59:C69) -> 0 | D70: =SUM(D59:D69) -> 0 | E70: =SUM(E59:E69) -> 0 | F70: =SUM(F59:F69) -> 0 | G70: =SUM(G59:G69) -> 0 | H70: =SUM(H59:H69) -> 0 | I70: =SUM(I59:I69) -> 0 | J70: =SUM(J59:J69) -> 0 | ... N70: =SUM(N59:N69) -> 0
A71: Décaissements
A72: Salaire Net | C72: ='[1]Prévisions Dépenses-Décaiss'!C44 -> 0 | D72: ='[1]Prévisions Dépenses-Décaiss'!D44 -> 0 | E72: ='[1]Prévisions Dépenses-Décaiss'!E44 -> 0 | F72: ='[1]Prévisions Dépenses-Décaiss'!F44 -> 0 | G72: ='[1]Prévisions Dépenses-Décaiss'!G44 -> 0 | H72: ='[1]Prévisions Dépenses-Décaiss'!H44 -> 0 | I72: ='[1]Prévisions Dépenses-Décaiss'!I44 -> 0 | J72: ='[1]Prévisions Dépenses-Décaiss'!J44 -> 0 | ... N72: ='[1]Prévisions Dépenses-Décaiss'!N44 -> 0
A73: IRG | C73: ='[1]Prévisions Dépenses-Décaiss'!C45 -> 0 | D73: ='[1]Prévisions Dépenses-Décaiss'!D45 -> 0 | E73: ='[1]Prévisions Dépenses-Décaiss'!E45 -> 0 | F73: ='[1]Prévisions Dépenses-Décaiss'!F45 -> 0 | G73: ='[1]Prévisions Dépenses-Décaiss'!G45 -> 0 | H73: ='[1]Prévisions Dépenses-Décaiss'!H45 -> 0 | I73: ='[1]Prévisions Dépenses-Décaiss'!I45 -> 0 | J73: ='[1]Prévisions Dépenses-Décaiss'!J45 -> 0 | ... N73: ='[1]Prévisions Dépenses-Décaiss'!N45 -> 0
A74: Secu 35% | C74: ='[1]Prévisions Dépenses-Décaiss'!C46 -> 0 | D74: ='[1]Prévisions Dépenses-Décaiss'!D46 -> 0 | E74: ='[1]Prévisions Dépenses-Décaiss'!E46 -> 0 | F74: ='[1]Prévisions Dépenses-Décaiss'!F46 -> 0 | G74: ='[1]Prévisions Dépenses-Décaiss'!G46 -> 0 | H74: ='[1]Prévisions Dépenses-Décaiss'!H46 -> 0 | I74: ='[1]Prévisions Dépenses-Décaiss'!I46 -> 0 | J74: ='[1]Prévisions Dépenses-Décaiss'!J46 -> 0 | ... N74: ='[1]Prévisions Dépenses-Décaiss'!N46 -> 0
A75: Abon.tel | C75: ='[1]Prévisions Dépenses-Décaiss'!C47 -> 0 | D75: ='[1]Prévisions Dépenses-Décaiss'!D47 -> 0 | E75: ='[1]Prévisions Dépenses-Décaiss'!E47 -> 0 | F75: ='[1]Prévisions Dépenses-Décaiss'!F47 -> 0 | G75: ='[1]Prévisions Dépenses-Décaiss'!G47 -> 0 | H75: ='[1]Prévisions Dépenses-Décaiss'!H47 -> 0 | I75: ='[1]Prévisions Dépenses-Décaiss'!I47 -> 0 | J75: ='[1]Prévisions Dépenses-Décaiss'!J47 -> 0 | ... N75: ='[1]Prévisions Dépenses-Décaiss'!N47 -> 0
A76: Loyer | C76: ='[1]Prévisions Dépenses-Décaiss'!C48 -> 0 | D76: ='[1]Prévisions Dépenses-Décaiss'!D48 -> 0 | E76: ='[1]Prévisions Dépenses-Décaiss'!E48 -> 0 | F76: ='[1]Prévisions Dépenses-Décaiss'!F48 -> 0 | G76: ='[1]Prévisions Dépenses-Décaiss'!G48 -> 0 | H76: ='[1]Prévisions Dépenses-Décaiss'!H48 -> 0 | I76: ='[1]Prévisions Dépenses-Décaiss'!I48 -> 0 | J76: ='[1]Prévisions Dépenses-Décaiss'!J48 -> 0 | ... N76: ='[1]Prévisions Dépenses-Décaiss'!N48 -> 0
A77: G50 Hors IRG | B77: TAP | C77: ='[1]Prévisions Dépenses-Décaiss'!C50 -> 0 | D77: ='[1]Prévisions Dépenses-Décaiss'!D50 -> 0 | E77: ='[1]Prévisions Dépenses-Décaiss'!E50 -> 0 | F77: ='[1]Prévisions Dépenses-Décaiss'!F50 -> 0 | G77: ='[1]Prévisions Dépenses-Décaiss'!G50 -> 0 | H77: ='[1]Prévisions Dépenses-Décaiss'!H50 -> 0 | I77: ='[1]Prévisions Dépenses-Décaiss'!I50 -> 0 | J77: ='[1]Prévisions Dépenses-Décaiss'!J50 -> 0 | ... N77: ='[1]Prévisions Dépenses-Décaiss'!N50 -> 0
B78: TVA | C78: ='[1]Prévisions Dépenses-Décaiss'!C51 -> 0 | D78: ='[1]Prévisions Dépenses-Décaiss'!D51 -> 0 | E78: ='[1]Prévisions Dépenses-Décaiss'!E51 -> 0 | F78: ='[1]Prévisions Dépenses-Décaiss'!F51 -> 0 | G78: ='[1]Prévisions Dépenses-Décaiss'!G51 -> 0 | H78: ='[1]Prévisions Dépenses-Décaiss'!H51 -> 0 | I78: ='[1]Prévisions Dépenses-Décaiss'!I51 -> 0 | J78: ='[1]Prévisions Dépenses-Décaiss'!J51 -> 0 | ... N78: ='[1]Prévisions Dépenses-Décaiss'!N51 -> 0
B79: Acompte IBS | C79: ='[1]Prévisions Dépenses-Décaiss'!C52 -> 0 | D79: ='[1]Prévisions Dépenses-Décaiss'!D52 -> 0 | E79: ='[1]Prévisions Dépenses-Décaiss'!E52 -> 0 | F79: ='[1]Prévisions Dépenses-Décaiss'!F52 -> 0 | G79: ='[1]Prévisions Dépenses-Décaiss'!G52 -> 0 | H79: ='[1]Prévisions Dépenses-Décaiss'!H52 -> 0 | I79: ='[1]Prévisions Dépenses-Décaiss'!I52 -> 0 | J79: ='[1]Prévisions Dépenses-Décaiss'!J52 -> 0 | ... N79: ='[1]Prévisions Dépenses-Décaiss'!N52 -> 0
A80: Achats materiels | C80: ='[1]Prévisions Dépenses-Décaiss'!C53 -> 0 | D80: ='[1]Prévisions Dépenses-Décaiss'!D53 -> 0 | E80: ='[1]Prévisions Dépenses-Décaiss'!E53 -> 0 | F80: ='[1]Prévisions Dépenses-Décaiss'!F53 -> 0 | G80: ='[1]Prévisions Dépenses-Décaiss'!G53 -> 0 | H80: ='[1]Prévisions Dépenses-Décaiss'!H53 -> 0 | I80: ='[1]Prévisions Dépenses-Décaiss'!I53 -> 0 | J80: ='[1]Prévisions Dépenses-Décaiss'!J53 -> 0 | ... N80: ='[1]Prévisions Dépenses-Décaiss'!N53 -> 0
A81: Autres | C81: ='[1]Prévisions Dépenses-Décaiss'!C54 -> 0 | D81: ='[1]Prévisions Dépenses-Décaiss'!D54 -> 0 | E81: ='[1]Prévisions Dépenses-Décaiss'!E54 -> 0 | F81: ='[1]Prévisions Dépenses-Décaiss'!F54 -> 0 | G81: ='[1]Prévisions Dépenses-Décaiss'!G54 -> 0 | H81: ='[1]Prévisions Dépenses-Décaiss'!H54 -> 0 | I81: ='[1]Prévisions Dépenses-Décaiss'!I54 -> 0 | J81: ='[1]Prévisions Dépenses-Décaiss'!J54 -> 0 | ... N81: ='[1]Prévisions Dépenses-Décaiss'!N54 -> 0
A82: TOTAL Décaissements | C82: =SUM(C72:C81) -> 0 | D82: =SUM(D72:D81) -> 0 | E82: =SUM(E72:E81) -> 0 | F82: =SUM(F72:F81) -> 0 | G82: =SUM(G72:G81) -> 0 | H82: =SUM(H72:H81) -> 0 | I82: =SUM(I72:I81) -> 0 | J82: =SUM(J72:J81) -> 0 | ... N82: =SUM(N72:N81) -> 0
A83: Trésorerie initiale | C83: =N52 -> 0 | D83: =C87 -> 0 | E83: =D87 -> 0 | F83: =E87 -> 0 | G83: =F87 -> 0 | H83: =G87 -> 0 | I83: =H87 -> 0 | J83: =I87 -> 0 | K83: =J87 -> 0 | ... N83: =M87 -> 0
A84: Encaissements | C84: =C70 -> 0 | D84: =D70 -> 0 | E84: =E70 -> 0 | F84: =F70 -> 0 | G84: =G70 -> 0 | H84: =H70 -> 0 | I84: =I70 -> 0 | J84: =J70 -> 0 | ... N84: =N70 -> 0
A85: Décaissements | C85: =C82 -> 0 | D85: =D82 -> 0 | E85: =E82 -> 0 | F85: =F82 -> 0 | G85: =G82 -> 0 | H85: =H82 -> 0 | I85: =I82 -> 0 | J85: =J82 -> 0 | ... N85: =N82 -> 0
A86: Solde periode | C86: =C84-C85 -> 0 | D86: =D84-D85 -> 0 | E86: =E84-E85 -> 0 | F86: =F84-F85 -> 0 | G86: =G84-G85 -> 0 | H86: =H84-H85 -> 0 | I86: =I84-I85 -> 0 | J86: =J84-J85 -> 0 | ... N86: =N84-N85 -> 0
A87: Trésorerie finale | C87: =C83+C86 -> 0 | D87: =D83+D86 -> 0 | E87: =E83+E86 -> 0 | F87: =F83+F86 -> 0 | G87: =G83+G86 -> 0 | H87: =H83+H86 -> 0 | I87: =I83+I86 -> 0 | J87: =J83+J86 -> 0 | ... N87: =N83+N86 -> 0
A92: Elements Periodes | C92: Juillet 1-7 | D92: Juillet 8-15 | E92: Juillet 16-23 | F92: Juillet 24-31 | G92: Aout 1-7 | H92: Aout 8-15 | I92: Aout 16-23 | J92: Aout 24-31 | K92: Septembre 1-7 | L92: Septembre 8-15 | M92: Septembre 16-23 | N92: Septembre 24-30
A93: Encaissements
A94: Clients | B94: Henkel | C94: ='[1]Prévisions Entrées-Encaiss'!C59 -> 0 | D94: ='[1]Prévisions Entrées-Encaiss'!D59 -> 0 | E94: ='[1]Prévisions Entrées-Encaiss'!E59 -> 0 | F94: ='[1]Prévisions Entrées-Encaiss'!F59 -> 0 | G94: ='[1]Prévisions Entrées-Encaiss'!G59 -> 0 | H94: ='[1]Prévisions Entrées-Encaiss'!H59 -> 0 | I94: ='[1]Prévisions Entrées-Encaiss'!I59 -> 0 | J94: ='[1]Prévisions Entrées-Encaiss'!J59 -> 0 | ... N94: ='[1]Prévisions Entrées-Encaiss'!N59 -> 0
B95: KNAUF | C95: ='[1]Prévisions Entrées-Encaiss'!C60 -> 0 | D95: ='[1]Prévisions Entrées-Encaiss'!D60 -> 0 | E95: ='[1]Prévisions Entrées-Encaiss'!E60 -> 0 | F95: ='[1]Prévisions Entrées-Encaiss'!F60 -> 0 | G95: ='[1]Prévisions Entrées-Encaiss'!G60 -> 0 | H95: ='[1]Prévisions Entrées-Encaiss'!H60 -> 0 | I95: ='[1]Prévisions Entrées-Encaiss'!I60 -> 0 | J95: ='[1]Prévisions Entrées-Encaiss'!J60 -> 0 | ... N95: ='[1]Prévisions Entrées-Encaiss'!N60 -> 0
B96: MyTeamConnect | C96: ='[1]Prévisions Entrées-Encaiss'!C61 -> 0 | D96: ='[1]Prévisions Entrées-Encaiss'!D61 -> 0 | E96: ='[1]Prévisions Entrées-Encaiss'!E61 -> 0 | F96: ='[1]Prévisions Entrées-Encaiss'!F61 -> 0 | G96: ='[1]Prévisions Entrées-Encaiss'!G61 -> 0 | H96: ='[1]Prévisions Entrées-Encaiss'!H61 -> 0 | I96: ='[1]Prévisions Entrées-Encaiss'!I61 -> 0 | J96: ='[1]Prévisions Entrées-Encaiss'!J61 -> 0 | ... N96: ='[1]Prévisions Entrées-Encaiss'!N61 -> 0
B97: Lafarge | C97: ='[1]Prévisions Entrées-Encaiss'!C62 -> 0 | D97: ='[1]Prévisions Entrées-Encaiss'!D62 -> 0 | E97: ='[1]Prévisions Entrées-Encaiss'!E62 -> 0 | F97: ='[1]Prévisions Entrées-Encaiss'!F62 -> 0 | G97: ='[1]Prévisions Entrées-Encaiss'!G62 -> 0 | H97: ='[1]Prévisions Entrées-Encaiss'!H62 -> 0 | I97: ='[1]Prévisions Entrées-Encaiss'!I62 -> 0 | J97: ='[1]Prévisions Entrées-Encaiss'!J62 -> 0 | ... N97: ='[1]Prévisions Entrées-Encaiss'!N62 -> 0
B98: DIGITAL NATIVES | C98: ='[1]Prévisions Entrées-Encaiss'!C63 -> 0 | D98: ='[1]Prévisions Entrées-Encaiss'!D63 -> 0 | E98: ='[1]Prévisions Entrées-Encaiss'!E63 -> 0 | F98: ='[1]Prévisions Entrées-Encaiss'!F63 -> 0 | G98: ='[1]Prévisions Entrées-Encaiss'!G63 -> 0 | H98: ='[1]Prévisions Entrées-Encaiss'!H63 -> 0 | I98: ='[1]Prévisions Entrées-Encaiss'!I63 -> 0 | J98: ='[1]Prévisions Entrées-Encaiss'!J63 -> 0 | ... N98: ='[1]Prévisions Entrées-Encaiss'!N63 -> 0
B99: Beyond | C99: ='[1]Prévisions Entrées-Encaiss'!C64 -> 0 | D99: ='[1]Prévisions Entrées-Encaiss'!D64 -> 0 | E99: ='[1]Prévisions Entrées-Encaiss'!E64 -> 0 | F99: ='[1]Prévisions Entrées-Encaiss'!F64 -> 0 | G99: ='[1]Prévisions Entrées-Encaiss'!G64 -> 0 | H99: ='[1]Prévisions Entrées-Encaiss'!H64 -> 0 | I99: ='[1]Prévisions Entrées-Encaiss'!I64 -> 0 | J99: ='[1]Prévisions Entrées-Encaiss'!J64 -> 0 | ... N99: ='[1]Prévisions Entrées-Encaiss'!N64 -> 0
B100: Kimmco | C100: ='[1]Prévisions Entrées-Encaiss'!C65 -> 0 | D100: ='[1]Prévisions Entrées-Encaiss'!D65 -> 0 | E100: ='[1]Prévisions Entrées-Encaiss'!E65 -> 0 | F100: ='[1]Prévisions Entrées-Encaiss'!F65 -> 0 | G100: ='[1]Prévisions Entrées-Encaiss'!G65 -> 0 | H100: ='[1]Prévisions Entrées-Encaiss'!H65 -> 0 | I100: ='[1]Prévisions Entrées-Encaiss'!I65 -> 0 | J100: ='[1]Prévisions Entrées-Encaiss'!J65 -> 0 | ... N100: ='[1]Prévisions Entrées-Encaiss'!N65 -> 0
B101: Insersite | C101: ='[1]Prévisions Entrées-Encaiss'!C66 -> 0 | D101: ='[1]Prévisions Entrées-Encaiss'!D66 -> 0 | E101: ='[1]Prévisions Entrées-Encaiss'!E66 -> 0 | F101: ='[1]Prévisions Entrées-Encaiss'!F66 -> 0 | G101: ='[1]Prévisions Entrées-Encaiss'!G66 -> 0 | H101: ='[1]Prévisions Entrées-Encaiss'!H66 -> 0 | I101: ='[1]Prévisions Entrées-Encaiss'!I66 -> 0 | J101: ='[1]Prévisions Entrées-Encaiss'!J66 -> 0 | ... N101: ='[1]Prévisions Entrées-Encaiss'!N66 -> 0
B102: In Solutions | C102: ='[1]Prévisions Entrées-Encaiss'!C67 -> 0 | D102: ='[1]Prévisions Entrées-Encaiss'!D67 -> 0 | E102: ='[1]Prévisions Entrées-Encaiss'!E67 -> 0 | F102: ='[1]Prévisions Entrées-Encaiss'!F67 -> 0 | G102: ='[1]Prévisions Entrées-Encaiss'!G67 -> 0 | H102: ='[1]Prévisions Entrées-Encaiss'!H67 -> 0 | I102: ='[1]Prévisions Entrées-Encaiss'!I67 -> 0 | J102: ='[1]Prévisions Entrées-Encaiss'!J67 -> 0 | ... N102: ='[1]Prévisions Entrées-Encaiss'!N67 -> 0
B103: Impact design | C103: ='[1]Prévisions Entrées-Encaiss'!C68 -> 0 | D103: ='[1]Prévisions Entrées-Encaiss'!D68 -> 0 | E103: ='[1]Prévisions Entrées-Encaiss'!E68 -> 0 | F103: ='[1]Prévisions Entrées-Encaiss'!F68 -> 0 | G103: ='[1]Prévisions Entrées-Encaiss'!G68 -> 0 | H103: ='[1]Prévisions Entrées-Encaiss'!H68 -> 0 | I103: ='[1]Prévisions Entrées-Encaiss'!I68 -> 0 | J103: ='[1]Prévisions Entrées-Encaiss'!J68 -> 0 | ... N103: ='[1]Prévisions Entrées-Encaiss'!N68 -> 0
A104: Autres ( tva déductibles,,,) | C104: ='[1]Prévisions Entrées-Encaiss'!C69 -> 0 | D104: ='[1]Prévisions Entrées-Encaiss'!D69 -> 0 | E104: ='[1]Prévisions Entrées-Encaiss'!E69 -> 0 | F104: ='[1]Prévisions Entrées-Encaiss'!F69 -> 0 | G104: ='[1]Prévisions Entrées-Encaiss'!G69 -> 0 | H104: ='[1]Prévisions Entrées-Encaiss'!H69 -> 0 | I104: ='[1]Prévisions Entrées-Encaiss'!I69 -> 0 | J104: ='[1]Prévisions Entrées-Encaiss'!J69 -> 0 | ... N104: ='[1]Prévisions Entrées-Encaiss'!N69 -> 0
A105: TOTAL Encaissements | C105: =SUM(C94:C104) -> 0 | D105: =SUM(D94:D104) -> 0 | E105: =SUM(E94:E104) -> 0 | F105: =SUM(F94:F104) -> 0 | G105: =SUM(G94:G104) -> 0 | H105: =SUM(H94:H104) -> 0 | I105: =SUM(I94:I104) -> 0 | J105: =SUM(J94:J104) -> 0 | ... N105: =SUM(N94:N104) -> 0
A106: Décaissements
A107: Salaire Net | C107: ='[1]Prévisions Dépenses-Décaiss'!C62 -> 0 | D107: ='[1]Prévisions Dépenses-Décaiss'!D62 -> 0 | E107: ='[1]Prévisions Dépenses-Décaiss'!E62 -> 0 | F107: ='[1]Prévisions Dépenses-Décaiss'!F62 -> 0 | G107: ='[1]Prévisions Dépenses-Décaiss'!G62 -> 0 | H107: ='[1]Prévisions Dépenses-Décaiss'!H62 -> 0 | I107: ='[1]Prévisions Dépenses-Décaiss'!I62 -> 0 | J107: ='[1]Prévisions Dépenses-Décaiss'!J62 -> 0 | ... N107: ='[1]Prévisions Dépenses-Décaiss'!N62 -> 0
A108: IRG | C108: ='[1]Prévisions Dépenses-Décaiss'!C63 -> 0 | D108: ='[1]Prévisions Dépenses-Décaiss'!D63 -> 0 | E108: ='[1]Prévisions Dépenses-Décaiss'!E63 -> 0 | F108: ='[1]Prévisions Dépenses-Décaiss'!F63 -> 0 | G108: ='[1]Prévisions Dépenses-Décaiss'!G63 -> 0 | H108: ='[1]Prévisions Dépenses-Décaiss'!H63 -> 0 | I108: ='[1]Prévisions Dépenses-Décaiss'!I63 -> 0 | J108: ='[1]Prévisions Dépenses-Décaiss'!J63 -> 0 | ... N108: ='[1]Prévisions Dépenses-Décaiss'!N63 -> 0
A109: Secu 35% | C109: ='[1]Prévisions Dépenses-Décaiss'!C64 -> 0 | D109: ='[1]Prévisions Dépenses-Décaiss'!D64 -> 0 | E109: ='[1]Prévisions Dépenses-Décaiss'!E64 -> 0 | F109: ='[1]Prévisions Dépenses-Décaiss'!F64 -> 0 | G109: ='[1]Prévisions Dépenses-Décaiss'!G64 -> 0 | H109: ='[1]Prévisions Dépenses-Décaiss'!H64 -> 0 | I109: ='[1]Prévisions Dépenses-Décaiss'!I64 -> 0 | J109: ='[1]Prévisions Dépenses-Décaiss'!J64 -> 0 | ... N109: ='[1]Prévisions Dépenses-Décaiss'!N64 -> 0
A110: Abon.tel | C110: ='[1]Prévisions Dépenses-Décaiss'!C65 -> 0 | D110: ='[1]Prévisions Dépenses-Décaiss'!D65 -> 0 | E110: ='[1]Prévisions Dépenses-Décaiss'!E65 -> 0 | F110: ='[1]Prévisions Dépenses-Décaiss'!F65 -> 0 | G110: ='[1]Prévisions Dépenses-Décaiss'!G65 -> 0 | H110: ='[1]Prévisions Dépenses-Décaiss'!H65 -> 0 | I110: ='[1]Prévisions Dépenses-Décaiss'!I65 -> 0 | J110: ='[1]Prévisions Dépenses-Décaiss'!J65 -> 0 | ... N110: ='[1]Prévisions Dépenses-Décaiss'!N65 -> 0
A111: Loyer | C111: ='[1]Prévisions Dépenses-Décaiss'!C66 -> 0 | D111: ='[1]Prévisions Dépenses-Décaiss'!D66 -> 0 | E111: ='[1]Prévisions Dépenses-Décaiss'!E66 -> 0 | F111: ='[1]Prévisions Dépenses-Décaiss'!F66 -> 0 | G111: ='[1]Prévisions Dépenses-Décaiss'!G66 -> 0 | H111: ='[1]Prévisions Dépenses-Décaiss'!H66 -> 0 | I111: ='[1]Prévisions Dépenses-Décaiss'!I66 -> 0 | J111: ='[1]Prévisions Dépenses-Décaiss'!J66 -> 0 | ... N111: ='[1]Prévisions Dépenses-Décaiss'!N66 -> 0
A112: G50 Hors IRG | B112: TAP | C112: ='[1]Prévisions Dépenses-Décaiss'!C68 -> 0 | D112: ='[1]Prévisions Dépenses-Décaiss'!D68 -> 0 | E112: ='[1]Prévisions Dépenses-Décaiss'!E68 -> 0 | F112: ='[1]Prévisions Dépenses-Décaiss'!F68 -> 0 | G112: ='[1]Prévisions Dépenses-Décaiss'!G68 -> 0 | H112: ='[1]Prévisions Dépenses-Décaiss'!H68 -> 0 | I112: ='[1]Prévisions Dépenses-Décaiss'!I68 -> 0 | J112: ='[1]Prévisions Dépenses-Décaiss'!J68 -> 0 | ... N112: ='[1]Prévisions Dépenses-Décaiss'!N68 -> 0
B113: TVA | C113: ='[1]Prévisions Dépenses-Décaiss'!C69 -> 0 | D113: ='[1]Prévisions Dépenses-Décaiss'!D69 -> 0 | E113: ='[1]Prévisions Dépenses-Décaiss'!E69 -> 0 | F113: ='[1]Prévisions Dépenses-Décaiss'!F69 -> 0 | G113: ='[1]Prévisions Dépenses-Décaiss'!G69 -> 0 | H113: ='[1]Prévisions Dépenses-Décaiss'!H69 -> 0 | I113: ='[1]Prévisions Dépenses-Décaiss'!I69 -> 0 | J113: ='[1]Prévisions Dépenses-Décaiss'!J69 -> 0 | ... N113: ='[1]Prévisions Dépenses-Décaiss'!N69 -> 0
B114: Acompte IBS | C114: ='[1]Prévisions Dépenses-Décaiss'!C70 -> 0 | D114: ='[1]Prévisions Dépenses-Décaiss'!D70 -> 0 | E114: ='[1]Prévisions Dépenses-Décaiss'!E70 -> 0 | F114: ='[1]Prévisions Dépenses-Décaiss'!F70 -> 0 | G114: ='[1]Prévisions Dépenses-Décaiss'!G70 -> 0 | H114: ='[1]Prévisions Dépenses-Décaiss'!H70 -> 0 | I114: ='[1]Prévisions Dépenses-Décaiss'!I70 -> 0 | J114: ='[1]Prévisions Dépenses-Décaiss'!J70 -> 0 | ... N114: ='[1]Prévisions Dépenses-Décaiss'!N70 -> 0
A115: Achats materiels | C115: ='[1]Prévisions Dépenses-Décaiss'!C71 -> 0 | D115: ='[1]Prévisions Dépenses-Décaiss'!D71 -> 0 | E115: ='[1]Prévisions Dépenses-Décaiss'!E71 -> 0 | F115: ='[1]Prévisions Dépenses-Décaiss'!F71 -> 0 | G115: ='[1]Prévisions Dépenses-Décaiss'!G71 -> 0 | H115: ='[1]Prévisions Dépenses-Décaiss'!H71 -> 0 | I115: ='[1]Prévisions Dépenses-Décaiss'!I71 -> 0 | J115: ='[1]Prévisions Dépenses-Décaiss'!J71 -> 0 | ... N115: ='[1]Prévisions Dépenses-Décaiss'!N71 -> 0
A116: Autres | C116: ='[1]Prévisions Dépenses-Décaiss'!C72 -> 0 | D116: ='[1]Prévisions Dépenses-Décaiss'!D72 -> 0 | E116: ='[1]Prévisions Dépenses-Décaiss'!E72 -> 0 | F116: ='[1]Prévisions Dépenses-Décaiss'!F72 -> 0 | G116: ='[1]Prévisions Dépenses-Décaiss'!G72 -> 0 | H116: ='[1]Prévisions Dépenses-Décaiss'!H72 -> 0 | I116: ='[1]Prévisions Dépenses-Décaiss'!I72 -> 0 | J116: ='[1]Prévisions Dépenses-Décaiss'!J72 -> 0 | ... N116: ='[1]Prévisions Dépenses-Décaiss'!N72 -> 0
A117: TOTAL Décaissements | C117: =SUM(C107:C116) -> 0 | D117: =SUM(D107:D116) -> 0 | E117: =SUM(E107:E116) -> 0 | F117: =SUM(F107:F116) -> 0 | G117: =SUM(G107:G116) -> 0 | H117: =SUM(H107:H116) -> 0 | I117: =SUM(I107:I116) -> 0 | J117: =SUM(J107:J116) -> 0 | ... N117: =SUM(N107:N116) -> 0
A118: Trésorerie initiale | C118: =N87 -> 0 | D118: =C122 -> 0 | E118: =D122 -> 0 | F118: =E122 -> 0 | G118: =F122 -> 0 | H118: =G122 -> 0 | I118: =H122 -> 0 | J118: =I122 -> 0 | K118: =J122 -> 0 | ... N118: =M122 -> 0
A119: Encaissements | C119: =C105 -> 0 | D119: =D105 -> 0 | E119: =E105 -> 0 | F119: =F105 -> 0 | G119: =G105 -> 0 | H119: =H105 -> 0 | I119: =I105 -> 0 | J119: =J105 -> 0 | ... N119: =N105 -> 0
A120: Décaissements | C120: =C117 -> 0 | D120: =D117 -> 0 | E120: =E117 -> 0 | F120: =F117 -> 0 | G120: =G117 -> 0 | H120: =H117 -> 0 | I120: =I117 -> 0 | J120: =J117 -> 0 | ... N120: =N117 -> 0
A121: Solde periode | C121: =C119-C120 -> 0 | D121: =D119-D120 -> 0 | E121: =E119-E120 -> 0 | F121: =F119-F120 -> 0 | G121: =G119-G120 -> 0 | H121: =H119-H120 -> 0 | I121: =I119-I120 -> 0 | J121: =J119-J120 -> 0 | ... N121: =N119-N120 -> 0
A122: Trésorerie finale | C122: =C118+C121 -> 0 | D122: =D118+D121 -> 0 | E122: =E118+E121 -> 0 | F122: =F118+F121 -> 0 | G122: =G118+G121 -> 0 | H122: =H118+H121 -> 0 | I122: =I118+I121 -> 0 | J122: =J118+J121 -> 0 | ... N122: =N118+N121 -> 0
A125: Elements Periodes | C125: Octobre 1-7 | D125: Octobre 8-15 | E125: Octobre 16-23 | F125: Octobre 24-30 | G125: Novembre 1-7 | H125: Novembre 8-15 | I125: Novembre 16-23 | J125: Novembre 24-30 | K125: Decembre 1-7 | L125: Decembre 8-15 | M125: Decembre 16-23 | N125: Decembre 24-30 | O125: Janvier 1-7 | P125: Janvier 8-15 | Q125: Janvier 16-23 | R125: Janvier 24-31 | S125: TOTAL
A126: Encaissements
A127: Clients | B127: Hhenkel | C127: ='[1]Prévisions Entrées-Encaiss'!C76 -> 0 | D127: ='[1]Prévisions Entrées-Encaiss'!D76 -> 0 | E127: ='[1]Prévisions Entrées-Encaiss'!E76 -> 0 | F127: ='[1]Prévisions Entrées-Encaiss'!F76 -> 0 | G127: ='[1]Prévisions Entrées-Encaiss'!G76 -> 0 | H127: ='[1]Prévisions Entrées-Encaiss'!H76 -> 0 | I127: ='[1]Prévisions Entrées-Encaiss'!I76 -> 0 | J127: ='[1]Prévisions Entrées-Encaiss'!J76 -> 0 | ... R127: ='[1]Prévisions Entrées-Encaiss'!R76 -> 0 | S127: =SUM(C24:N24,C59:N59,C94:N94,C127:R127) -> 0
B128: KNAUF | C128: ='[1]Prévisions Entrées-Encaiss'!C77 -> 0 | D128: ='[1]Prévisions Entrées-Encaiss'!D77 -> 0 | E128: ='[1]Prévisions Entrées-Encaiss'!E77 -> 0 | F128: ='[1]Prévisions Entrées-Encaiss'!F77 -> 0 | G128: ='[1]Prévisions Entrées-Encaiss'!G77 -> 0 | H128: ='[1]Prévisions Entrées-Encaiss'!H77 -> 0 | I128: ='[1]Prévisions Entrées-Encaiss'!I77 -> 0 | J128: ='[1]Prévisions Entrées-Encaiss'!J77 -> 0 | ... R128: ='[1]Prévisions Entrées-Encaiss'!R77 -> 0 | S128: =SUM(C25:N25,C60:N60,C95:N95,C128:R128) -> 0
B129: MyTeamConnect | C129: ='[1]Prévisions Entrées-Encaiss'!C78 -> 0 | D129: ='[1]Prévisions Entrées-Encaiss'!D78 -> 0 | E129: ='[1]Prévisions Entrées-Encaiss'!E78 -> 0 | F129: ='[1]Prévisions Entrées-Encaiss'!F78 -> 0 | G129: ='[1]Prévisions Entrées-Encaiss'!G78 -> 0 | H129: ='[1]Prévisions Entrées-Encaiss'!H78 -> 0 | I129: ='[1]Prévisions Entrées-Encaiss'!I78 -> 0 | J129: ='[1]Prévisions Entrées-Encaiss'!J78 -> 0 | ... R129: ='[1]Prévisions Entrées-Encaiss'!R78 -> 0 | S129: =SUM(C26:N26,C61:N61,C96:N96,C129:R129) -> 0
B130: Lafarge | C130: ='[1]Prévisions Entrées-Encaiss'!C79 -> 0 | D130: ='[1]Prévisions Entrées-Encaiss'!D79 -> 0 | E130: ='[1]Prévisions Entrées-Encaiss'!E79 -> 0 | F130: ='[1]Prévisions Entrées-Encaiss'!F79 -> 0 | G130: ='[1]Prévisions Entrées-Encaiss'!G79 -> 0 | H130: ='[1]Prévisions Entrées-Encaiss'!H79 -> 0 | I130: ='[1]Prévisions Entrées-Encaiss'!I79 -> 0 | J130: ='[1]Prévisions Entrées-Encaiss'!J79 -> 0 | ... R130: ='[1]Prévisions Entrées-Encaiss'!R79 -> 0 | S130: =SUM(C27:N27,C62:N62,C97:N97,C130:R130) -> 0
...
